pycrits/__init__.py
pycrits/access_token.py
pycrits/actor.py
pycrits/backdoor.py
pycrits/campaign.py
pycrits/certificate.py
pycrits/comment.py
pycrits/common.py
pycrits/connection.py
pycrits/domain.py
pycrits/email.py
pycrits/errors.py
pycrits/event.py
pycrits/exploit.py
pycrits/indicator.py
pycrits/ip.py
pycrits/logger.py
pycrits/pcap.py
pycrits/raw.py
pycrits/request.py
pycrits/sample.py
pycrits/screenshot.py
pycrits/signature.py
pycrits/target.py
pycrits/vocabulary.py
pycrits-1.0.3.dist-info/METADATA
pycrits-1.0.3.dist-info/RECORD
pycrits-1.0.3.dist-info/WHEEL
pycrits-1.0.3.dist-info/top_level.txt
