Metadata-Version: 2.1
Name: pycrits
Version: 1.0.3
Summary: Python Library for CRITs
Home-page: UNKNOWN
Author: Carter Church
Author-email: carter.church@dynetics.com
License: MIT
Keywords: pycrits
Platform: UNKNOWN
Classifier: Development Status :: 3 - Alpha
Classifier: Intended Audience :: Developers
Classifier: Topic :: Software Development :: Build Tools
Classifier: License :: OSI Approved :: MIT License
Classifier: Programming Language :: Python :: 2.7
Requires-Dist: requests
